Workbook

Sheet Instrucciones
A1: Data Analyst Academy · Auditoría de un modelo con errores
A3: Objetivo: encontrar y corregir SIETE errores sembrados en el modelo de resultados de 2025.
A4: Cómo trabajar: usa Fórmulas > Auditoría de fórmulas (precedentes, dependientes, evaluar) y Ctrl+` para ver fórmulas.
A5: Corrige las fórmulas (no pegues valores). Cuando todos los controles de «Comprobacion» estén en ✔, has terminado.
A6: Después compara con el libro de solución, donde la hoja «Errores» describe cada fallo.
A8: Cómo se corrige: la hoja «Comprobacion» compara tu respuesta con el valor esperado y marca ✔ o ✘.
A9: Datos: muestra reproducible del dataset sintético Lumen (semilla fija). No son datos reales.
A10: Nombres de función: se muestran en español / inglés. El archivo guarda siempre los nombres en inglés.
A11: Separadores: en un Excel en español de España los argumentos se separan con «;» y el decimal es «,».

Sheet Supuestos
A1: Supuestos
A2: Descuento medio sobre el precio bruto | B2: 0.08
A3: Coste unitario (€ por unidad) | B3: 44.69
A4: Gastos fijos mensuales (€) | B4: 532000
A5: Tipo impositivo | B5: 21

Sheet Modelo
A1: Modelo de resultados 2025 (euros)
A4: Concepto | B4: ene | C4: feb | D4: mar | E4: abr | F4: may | G4: jun | H4: jul | I4: ago | J4: sep | K4: oct | L4: nov | M4: dic | N4: Total 2025
A5: Unidades | B5: 37267 | C5: 38240 | D5: 37636 | E5: 37608 | F5: 41377 | G5: 41407 | H5: 54431 | I5: 58607 | J5: 49471 | K5: 55331 | L5: 55788 | M5: 63315 | N5: =SUM(B5:M5)
A6: Precio bruto medio (€) | B6: 74.62 | C6: 71.04 | D6: 87.75 | E6: 86.43 | F6: 85.89 | G6: 85.16 | H6: 72.05 | I6: 72.6 | J6: 86.53 | K6: 86.65 | L6: 85.65 | M6: 80.73 | N6: =N7/N5
A7: Ingresos brutos | B7: =B5*B6 | C7: =C5*C6 | D7: =D5*D6 | E7: =E5*E6 | F7: =F5*F6 | G7: =G5*G6 | H7: =H5*H6 | I7: =I5*I6 | ... M7: =M5*M6 | N7: =SUM(B7:M7)
A8: Descuento | B8: =B7*Supuestos!$B$2 | C8: =C7*Supuestos!$B$2 | D8: =D7*Supuestos!$B$2 | E8: =E7*Supuestos!$B$2 | F8: =F7*Supuestos!F2 | G8: =G7*Supuestos!$B$2 | H8: =H7*Supuestos!$B$2 | I8: =I7*Supuestos!$B$2 | J8: =J7*Supuestos!$B$2 | K8: =K7*Supuestos!$B$2 | L8: =L7*Supuestos!$B$2 | M8: =M7*Supuestos!$B$2 | N8: =SUM(B8:M8)
A9: Ingresos netos | B9: =B7-B8 | C9: =C7-C8 | D9: =D7-D8 | E9: =E7-E8 | F9: =F7-F8 | G9: =G7-G8 | H9: =H7-H8 | I9: =I7-I8 | ... M9: =M7-M8 | N9: =SUM(B9:L9)
A10: Coste de ventas | B10: =B5*Supuestos!$B$3 | C10: =C5*Supuestos!$B$3 | D10: =D5*Supuestos!$B$3 | E10: =E5*Supuestos!$B$3 | F10: =F5*Supuestos!$B$3 | G10: =G5*Supuestos!$B$3 | H10: 2627123 | I10: =I5*Supuestos!$B$3 | J10: =J5*Supuestos!$B$3 | K10: =K5*Supuestos!$B$3 | L10: =L5*Supuestos!$B$3 | M10: =M5*Supuestos!$B$3 | N10: =SUM(B10:M10)
A11: Margen bruto | B11: =B9-B10 | C11: =C9-C10 | D11: =D9-D10 | E11: =E9-E10 | F11: =F9-F10 | G11: =G9-G10 | H11: =H9-H10 | I11: =I9-I10 | ... M11: =M9-M10 | N11: =SUM(B11:M11)
A12: Gastos fijos | B12: =Supuestos!$B$4 | C12: =Supuestos!$B$4 | D12: =Supuestos!$B$4 | E12: =Supuestos!$B$4 | F12: =Supuestos!$B$4 | G12: =Supuestos!$B$4 | H12: =Supuestos!$B$4 | I12: =Supuestos!$B$4 | ... M12: =Supuestos!$B$4 | N12: =SUM(B12:M12)
A13: EBIT | B13: =B11-B12 | C13: =C11-C12 | D13: =D11-D12 | E13: =E11-E12 | F13: =F11-F12 | G13: =G11-G12 | H13: =H11-H12 | I13: =I11-I12 | ... M13: =M11-M12 | N13: =SUM(B13:M13)+B13
A14: Impuestos | B14: =MAX(0,B13)*Supuestos!$B$5 | C14: =MAX(0,C13)*Supuestos!$B$5 | D14: =MAX(0,D13)*Supuestos!$B$5 | E14: =MAX(0,E13)*Supuestos!$B$5 | F14: =MAX(0,F13)*Supuestos!$B$5 | G14: =MAX(0,G13)*Supuestos!$B$5 | H14: =MAX(0,H13)*Supuestos!$B$5 | I14: =MAX(0,I13)*Supuestos!$B$5 | ... M14: =MAX(0,M13)*Supuestos!$B$5 | N14: =SUM(B14:M14)
A15: Resultado neto | B15: =B13-B14 | C15: =C13-C14 | D15: =D13-D14 | E15: =E13-E14 | F15: =F13-F14 | G15: =G13-G14 | H15: =H13-H14 | I15: =I13-I14 | ... M15: =M13-M14 | N15: =SUM(B15:M15)
A16: Margen bruto % s/ ingresos netos | B16: =B11/B9 | C16: =C11/C9 | D16: =D11/D9 | E16: =E11/E9 | F16: =F11/F9 | G16: =G11/G9 | H16: =H11/H9 | I16: =I11/I9 | J16: =J11/J10 | K16: =K11/K9 | L16: =L11/L9 | M16: =M11/M9 | N16: =N11/N9

Sheet Comprobacion
A1: Autocomprobación
A3: Nº | B3: Qué se comprueba | C3: Tu respuesta | D3: Esperado | E3: Resultado
A4: 1 | B4: Ingresos netos totales (Modelo!N9) | C4: =IF(Modelo!N9="","",Modelo!N9) | D4: 42570224 | E4: =IF(C4="","—",IF(ISNUMBER(D4),IF(ISNUMBER(C4),IF(ABS(C4-D4)<=0.5,"✔","✘"),"✘"),IF(C4=D4,"✔","✘")))
A5: 2 | B5: Coste de ventas total (Modelo!N10) | C5: =IF(Modelo!N10="","",Modelo!N10) | D5: 25494662 | E5: =IF(C5="","—",IF(ISNUMBER(D5),IF(ISNUMBER(C5),IF(ABS(C5-D5)<=0.5,"✔","✘"),"✘"),IF(C5=D5,"✔","✘")))
A6: 3 | B6: Descuento de mayo (Modelo!F8) | C6: =IF(Modelo!F8="","",Modelo!F8) | D6: 284309.64 | E6: =IF(C6="","—",IF(ISNUMBER(D6),IF(ISNUMBER(C6),IF(ABS(C6-D6)<=0.5,"✔","✘"),"✘"),IF(C6=D6,"✔","✘")))
A7: 4 | B7: Unidades totales (Modelo!N5) | C7: =IF(Modelo!N5="","",Modelo!N5) | D7: 570478 | E7: =IF(C7="","—",IF(ISNUMBER(D7),IF(ISNUMBER(C7),IF(ABS(C7-D7)<=0.5,"✔","✘"),"✘"),IF(C7=D7,"✔","✘")))
A8: 5 | B8: Margen bruto % de septiembre (Modelo!J16) | C8: =IF(Modelo!J16="","",Modelo!J16) | D8: 0.4386 | E8: =IF(C8="","—",IF(ISNUMBER(D8),IF(ISNUMBER(C8),IF(ABS(C8-D8)<=0.0005,"✔","✘"),"✘"),IF(C8=D8,"✔","✘")))
A9: 6 | B9: Impuestos totales (Modelo!N14) | C9: =IF(Modelo!N14="","",Modelo!N14) | D9: 2245228.1 | E9: =IF(C9="","—",IF(ISNUMBER(D9),IF(ISNUMBER(C9),IF(ABS(C9-D9)<=0.5,"✔","✘"),"✘"),IF(C9=D9,"✔","✘")))
A10: 7 | B10: EBIT total (Modelo!N13) | C10: =IF(Modelo!N13="","",Modelo!N13) | D10: 10691562 | E10: =IF(C10="","—",IF(ISNUMBER(D10),IF(ISNUMBER(C10),IF(ABS(C10-D10)<=0.5,"✔","✘"),"✘"),IF(C10=D10,"✔","✘")))
A11: 8 | B11: Coste de ventas de julio (Modelo!H10) | C11: =IF(Modelo!H10="","",Modelo!H10) | D11: 2432521.4 | E11: =IF(C11="","—",IF(ISNUMBER(D11),IF(ISNUMBER(C11),IF(ABS(C11-D11)<=0.5,"✔","✘"),"✘"),IF(C11=D11,"✔","✘")))
B13: Resumen | C13: =COUNTIF(E4:E11,"✔")&" de "&ROWS(E4:E11)&" correctas"
