Workbook

Sheet Instrucciones
A1: Data Analyst Academy · Verificar el trabajo de una IA
A3: Situación: un asistente de IA actualizó la hipótesis de descuento de un modelo de previsión por segmento.
A4: El resultado «tiene buena pinta», pero el asistente cometió CUATRO errores plausibles.
A5: Objetivo: aplicar el protocolo de cuatro controles (cuadre, muestreo, fórmulas visibles, casos límite),
A6: encontrar los errores, corregirlos y dejar todos los controles de «Comprobacion» en ✔.
A7: Importes en miles de euros (2025, pedidos completados).
A9: Cómo se corrige: la hoja «Comprobacion» compara tu respuesta con el valor esperado y marca ✔ o ✘.
A10: Datos: muestra reproducible del dataset sintético Lumen (semilla fija). No son datos reales.
A11: Nombres de función: se muestran en español / inglés. El archivo guarda siempre los nombres en inglés.
A12: Separadores: en un Excel en español de España los argumentos se separan con «;» y el decimal es «,».

Sheet Supuestos
A1: Supuestos
A2: Descuento objetivo | B2: 12

Sheet Prevision
A1: Segmento | B1: Ingresos 2025 | C1: Coste 2025 | D1: Descuento actual | E1: Ingresos escenario | F1: Coste escenario | G1: Margen | H1: Margen %
A2: nuevo | B2: 6104 | C2: 3926 | D2: 0.107 | E2: =B2*(1-Supuestos!$B$2)/(1-D2) | F2: =C2 | G2: =E2-F2 | H2: =G2/E2
A3: ocasional | B3: 9309 | C3: 5972 | D3: 0.107 | E3: =B3*(1-Supuestos!$B$2)/(1-D3) | F3: =C3 | G3: =E3-F3 | H3: =G3/B3
A4: habitual | B4: 17374 | C4: 11187 | D4: 0.107 | E4: =B4*(1-Supuestos!$B$2)/(1-D4) | F4: =C4 | G4: 5518.7 | H4: =G4/E4
A5: vip | B5: 13498 | C5: 8679 | D5: 0.109 | E5: =B5*(1-Supuestos!$B$2)/(1-D5) | F5: =C5 | G5: =E5-F5 | H5: =G5/E5
A6: Total | B6: =SUM(B2:B5) | C6: =SUM(C2:C5) | E6: =SUM(E2:E4) | F6: =SUM(F2:F5) | G6: =SUM(G2:G5) | H6: =G6/E6

Sheet Comprobacion
A1: Autocomprobación
A3: Nº | B3: Qué se comprueba | C3: Tu respuesta | D3: Esperado | E3: Resultado
A4: 1 | B4: Ingresos escenario total (Prevision!E6) | C4: =IF(Prevision!E6="","",Prevision!E6) | D4: 45641.06 | E4: =IF(C4="","—",IF(ISNUMBER(D4),IF(ISNUMBER(C4),IF(ABS(C4-D4)<=0.5,"✔","✘"),"✘"),IF(C4=D4,"✔","✘")))
A5: 2 | B5: Margen % del segmento ocasional (Prevision!H3) | C5: =IF(Prevision!H3="","",Prevision!H3) | D5: 0.349 | E5: =IF(C5="","—",IF(ISNUMBER(D5),IF(ISNUMBER(C5),IF(ABS(C5-D5)<=0.0005,"✔","✘"),"✘"),IF(C5=D5,"✔","✘")))
A6: 3 | B6: Margen % del segmento habitual (Prevision!H4) | C6: =IF(Prevision!H4="","",Prevision!H4) | D6: 0.3466 | E6: =IF(C6="","—",IF(ISNUMBER(D6),IF(ISNUMBER(C6),IF(ABS(C6-D6)<=0.0005,"✔","✘"),"✘"),IF(C6=D6,"✔","✘")))
A7: 4 | B7: Margen del segmento habitual (Prevision!G4) | C7: =IF(Prevision!G4="","",Prevision!G4) | D7: 5934.08 | E7: =IF(C7="","—",IF(ISNUMBER(D7),IF(ISNUMBER(C7),IF(ABS(C7-D7)<=0.5,"✔","✘"),"✘"),IF(C7=D7,"✔","✘")))
A8: 5 | B8: Margen total (Prevision!G6) | C8: =IF(Prevision!G6="","",Prevision!G6) | D8: 15877.06 | E8: =IF(C8="","—",IF(ISNUMBER(D8),IF(ISNUMBER(C8),IF(ABS(C8-D8)<=0.5,"✔","✘"),"✘"),IF(C8=D8,"✔","✘")))
A9: 6 | B9: Margen % total (Prevision!H6) | C9: =IF(Prevision!H6="","",Prevision!H6) | D9: 0.3479 | E9: =IF(C9="","—",IF(ISNUMBER(D9),IF(ISNUMBER(C9),IF(ABS(C9-D9)<=0.0005,"✔","✘"),"✘"),IF(C9=D9,"✔","✘")))
B11: Resumen | C11: =COUNTIF(E4:E9,"✔")&" de "&ROWS(E4:E9)&" correctas"
